{
  "cik": "0000077476",
  "ticker": "PEP",
  "issuer_name": "PepsiCo",
  "aliases": [],
  "document_structure": {
    "derivatives_note_heading": "",
    "market_risk_heading": "",
    "section_locations": {}
  },
  "filing_patterns": {
    "typical_note_numbering": "",
    "heading_variations_seen": [],
    "uses_cross_reference_in_10q": false,
    "market_risk_in_10k_only": false
  },
  "idiosyncrasies": {
    "recurring_phrases": [
      "net investment hedge",
      "cash flow hedge",
      "fair value hedging",
      "cross-currency",
      "interest rate swap",
      "commodity contract",
      "notional amount",
      "unrealized gain",
      "designated as hedging",
      "accumulated other comprehensive",
      "net investment hedging",
      "cash flow hedging"
    ],
    "non_gaap_metrics": [],
    "unusual_disclosure_patterns": [],
    "known_issues": []
  },
  "history": [
    {
      "filing_date": "2026-03-21",
      "form_type": "10-Q",
      "period_end": "2026-03-21",
      "processed_at": "2026-04-20T07:53:58Z",
      "sections_found": [
        "financial_instruments",
        "market_risk"
      ],
      "fields_extracted": 4,
      "fields_null": 15
    },
    {
      "filing_date": "2025-03-22",
      "form_type": "10-Q",
      "period_end": "2025-03-22",
      "processed_at": "2026-04-21T07:24:00Z",
      "sections_found": [
        "financial_instruments",
        "market_risk"
      ],
      "fields_extracted": 6,
      "fields_null": 13
    },
    {
      "filing_date": "2025-06-14",
      "form_type": "10-Q",
      "period_end": "2025-06-14",
      "processed_at": "2026-04-21T07:24:12Z",
      "sections_found": [
        "financial_instruments",
        "market_risk"
      ],
      "fields_extracted": 5,
      "fields_null": 14
    },
    {
      "filing_date": "2025-09-06",
      "form_type": "10-Q",
      "period_end": "2025-09-06",
      "processed_at": "2026-04-21T07:24:27Z",
      "sections_found": [
        "financial_instruments",
        "market_risk"
      ],
      "fields_extracted": 6,
      "fields_null": 13
    }
  ]
}
